README.md
setup.py
pique/cli.py
pique/pq.py
pique/themes.py
python_pique.egg-info/PKG-INFO
python_pique.egg-info/SOURCES.txt
python_pique.egg-info/dependency_links.txt
python_pique.egg-info/entry_points.txt
python_pique.egg-info/top_level.txt