Metadata-Version: 2.1
Name: python-pique
Version: 1.0.0
Summary: Query JSON from the CLI using Python syntax
Home-page: http://github.com/Pebaz/pique
Author: http://github.com/Pebaz
License: MIT
Platform: UNKNOWN
